biodem/__init__.py
biodem/cli_dem.py
biodem/constants/__init__.py
biodem/constants/default.py
biodem/constants/dict_key.py
biodem/constants/fname.py
biodem/constants/hparam_candidates.py
biodem/dem/__init__.py
biodem/dem/model.py
biodem/dem/pipeline.py
biodem/dem/rank.py
biodem/s2g/__init__.py
biodem/s2g/model.py
biodem/s2g/model_sparse.py
biodem/s2g/pipeline.py
biodem/utils/__init__.py
biodem/utils/data_ncv.py
biodem/utils/uni.py
bin/linux/pregv
bin/windows/pregv.exe
biodem-0.9.1.dist-info/METADATA
biodem-0.9.1.dist-info/WHEEL
biodem-0.9.1.dist-info/entry_points.txt
biodem-0.9.1.dist-info/licenses/LICENSE
biodem-0.9.1.dist-info/RECORD
