Metadata-Version: 2.3
Name: biodem
Version: 0.9.1
Summary: Dual-extraction method for phenotypic prediction and functional gene mining
Project-URL: Homepage, https://github.com/cma2015/DEM
Author-email: Chenhua Wu <chanhuawu@outlook.com>, Yanlin Ren <ryl1999@126.com>
License:                                  Apache License
License-File: LICENSE
Keywords: agriculture,bioinformatics,deep learning,machine learning,pytorch
Classifier: Development Status :: 4 - Beta
Classifier: Environment :: Console
Classifier: Intended Audience :: Science/Research
Classifier: License :: OSI Approved :: Apache Software License
Classifier: Natural Language :: English
Classifier: Operating System :: Microsoft :: Windows :: Windows 10
Classifier: Operating System :: Microsoft :: Windows :: Windows 11
Classifier: Operating System :: POSIX :: Linux
Classifier: Programming Language :: Python :: 3
Classifier: Programming Language :: Python :: 3.10
Classifier: Programming Language :: Python :: 3.11
Classifier: Programming Language :: Python :: 3.12
Classifier: Topic :: Scientific/Engineering :: Bio-Informatics
Requires-Python: <3.13,>=3.10
Requires-Dist: lightning>=2.4.0
Requires-Dist: litdata>=0.2.29
Requires-Dist: mosaicml-streaming>=0.8.0
Requires-Dist: numpy>=2.0
Requires-Dist: optuna-dashboard>=0.16.0
Requires-Dist: optuna>=4.0
Requires-Dist: polars>=1.9.0
Requires-Dist: pyarrow>=17.0
Requires-Dist: scikit-learn>=1.5.0
Requires-Dist: scipy>=1.13.0
Requires-Dist: tensorboard>=2.18.0
Requires-Dist: torch>=2.1.0
Requires-Dist: torchmetrics>=1.4.0
Requires-Dist: zstd>=1.5.5
